LICENSE
MANIFEST.in
README.md
setup.cfg
setup.py
versioneer.py
openpifpaf_posetrack/__init__.py
openpifpaf_posetrack/_version.py
openpifpaf_posetrack/backbone.py
openpifpaf_posetrack/benchmark.py
openpifpaf_posetrack/cocokpst.py
openpifpaf_posetrack/collate.py
openpifpaf_posetrack/constants.py
openpifpaf_posetrack/datasets.py
openpifpaf_posetrack/draw_poses.py
openpifpaf_posetrack/headmeta.py
openpifpaf_posetrack/heads.py
openpifpaf_posetrack/imagetotracking.py
openpifpaf_posetrack/metric.py
openpifpaf_posetrack/posetrack2017.py
openpifpaf_posetrack/posetrack2018.py
openpifpaf_posetrack/signal.py
openpifpaf_posetrack.egg-info/PKG-INFO
openpifpaf_posetrack.egg-info/SOURCES.txt
openpifpaf_posetrack.egg-info/dependency_links.txt
openpifpaf_posetrack.egg-info/requires.txt
openpifpaf_posetrack.egg-info/top_level.txt
openpifpaf_posetrack/decoder/__init__.py
openpifpaf_posetrack/decoder/pose_similarity.py
openpifpaf_posetrack/decoder/track_annotation.py
openpifpaf_posetrack/decoder/track_base.py
openpifpaf_posetrack/decoder/tracking_pose.py
openpifpaf_posetrack/decoder/pose_distance/__init__.py
openpifpaf_posetrack/decoder/pose_distance/crafted.py
openpifpaf_posetrack/decoder/pose_distance/euclidean.py
openpifpaf_posetrack/decoder/pose_distance/oks.py
openpifpaf_posetrack/encoder/__init__.py
openpifpaf_posetrack/encoder/annrescaler.py
openpifpaf_posetrack/encoder/single_image.py
openpifpaf_posetrack/encoder/tcaf.py
openpifpaf_posetrack/transforms/__init__.py
openpifpaf_posetrack/transforms/blank_past.py
openpifpaf_posetrack/transforms/camera_shift.py
openpifpaf_posetrack/transforms/crop.py
openpifpaf_posetrack/transforms/deinterlace.py
openpifpaf_posetrack/transforms/encoders.py
openpifpaf_posetrack/transforms/image.py
openpifpaf_posetrack/transforms/image_to_tracking.py
openpifpaf_posetrack/transforms/impute.py
openpifpaf_posetrack/transforms/normalize.py
openpifpaf_posetrack/transforms/pad.py
openpifpaf_posetrack/transforms/sample_pairing.py
openpifpaf_posetrack/transforms/scale.py
openpifpaf_posetrack/transforms/single_image.py
openpifpaf_posetrack/visualizer/__init__.py
openpifpaf_posetrack/visualizer/multitracking.py
openpifpaf_posetrack/visualizer/tcaf.py