Metadata-Version: 2.1
Name: openpifpaf-posetrack
Version: 0.3.0
Summary: OpenPifPaf plugin for Posetrack
Home-page: https://github.com/vita-epfl/openpifpaf_posetrack
Author: Sven Kreiss
Author-email: research@svenkreiss.com
License: MIT
Platform: UNKNOWN
Provides-Extra: test
Provides-Extra: eval
Provides-Extra: train
Provides-Extra: video
